typepigeon/__init__.py
typepigeon/to_json.py
typepigeon/to_type.py
typepigeon/types.py
typepigeon-2.0.4.dist-info/METADATA
typepigeon-2.0.4.dist-info/WHEEL
typepigeon-2.0.4.dist-info/licenses/LICENSE
typepigeon-2.0.4.dist-info/RECORD
