Metadata-Version: 2.4
Name: typepigeon
Version: 2.0.4
Summary: Python type converter
Project-URL: repository, https://github.com/zacharyburnett/TypePigeon.git
Project-URL: documentation, https://typepigeon.readthedocs.io
Author-email: Zach Burnett <zachary.r.burnett@gmail.com>
License:                     GNU GENERAL PUBLIC LICENSE
License-File: LICENSE
Requires-Python: >=3.7
Requires-Dist: python-dateutil
Provides-Extra: docs
Requires-Dist: dunamai; extra == 'docs'
Requires-Dist: m2r2; extra == 'docs'
Requires-Dist: sphinx; extra == 'docs'
Requires-Dist: sphinx-rtd-theme; extra == 'docs'
Requires-Dist: tomli; (python_version < '3.11') and extra == 'docs'
Provides-Extra: spatial
Requires-Dist: pyproj; extra == 'spatial'
Requires-Dist: shapely; extra == 'spatial'
Provides-Extra: test
Requires-Dist: pytest; extra == 'test'
Requires-Dist: pytest-cov; extra == 'test'
Requires-Dist: pytest-xdist; extra == 'test'
